pxm_liumou_Stable/__init__.py
pxm_liumou_Stable/dic.py
pxm_liumou_Stable/exists.py
pxm_liumou_Stable/pxm.py
pxm_liumou_Stable/read.py
pxm_liumou_Stable/write.py
pxm_liumou_stable-1.1.4.dist-info/METADATA
pxm_liumou_stable-1.1.4.dist-info/WHEEL
pxm_liumou_stable-1.1.4.dist-info/licenses/LICENSE
pxm_liumou_stable-1.1.4.dist-info/RECORD
