Metadata-Version: 2.4
Name: pxm_liumou_Stable
Version: 1.1.4
Summary: 这是一个Python编写的表格读写常用操作功能基础模块,基于openpyxl封装常用功能
Project-URL: Homepage, https://gitee.com/liumou_site/pxm
Project-URL: Bug Tracker, https://gitee.com/liumou_site/pxm/issues
Author-email: 坐公交也用券 <liumou.site@qq.com>
License-File: LICENSE
Classifier: License :: OSI Approved :: MIT License
Classifier: Operating System :: OS Independent
Classifier: Programming Language :: Python :: 3
Requires-Python: >=3.7
